{
    "photos": {
        "commercial": [
            {
                "id": "professional-1-cover-light_pm22em",
                "subtitle": "Unión Europea",
                "title": "Bomberos Comunarios",
                "type": "photo",
                "children": [
                    "professional-1-cover-light_pm22em",
                    "professional-1-2-light_jy3foq",
                    "professional-1-3-light_elbbdf",
                    "professional-1-4-light_ufb2xo",
                    "professional-1-5-light_fkqca6",
                    "professional-1-6-light_nilqnp",
                    "professional-1-7-light_h2bwo8",
                    "professional-1-8-light_cotchg",
                    "professional-1-9-light_qkb2q5",
                    "professional-1-10-light_ozc1bi",
                    "professional-1-11-light_nfdw59",
                    "professional-1-12-light_ybttul"
                ]
            },
            {
                "id": "professional-2-cover-light_laavuy",
                "subtitle": "Unión Europea",
                "title": "Recolección de frutos del Bosque",
                "type": "photo",
                "children": [
                    "professional-2-cover-light_laavuy",
                    "professional-2-1-light_hhxo0o",
                    "professional-2-2-light_iwu5eu",
                    "professional-2-3-light_apy3e9",
                    "professional-2-4-light_mmsdo6",
                    "professional-2-5-light_ubvnds",
                    "professional-2-6-light_dqukea",
                    "professional-2-7-light_mexb6j",
                    "professional-2-8-light_jiwu8z",
                    "professional-2-9-light_ufruia",
                    "professional-2-10-light_uwiudl",
                    "professional-2-11-light_utwzqa",
                    "professional-2-12-light_jthpv7"
                ]
            },
            {
                "id": "professional-3-cover-light_im3m8w",
                "subtitle": "Crillón Tours",
                "title": "Catálogo 2024",
                "type": "photo",
                "children": [
                    "professional-3-cover-light_im3m8w",
                    "professional-3-0-light_dklqtm",
                    "professional-3-1-light_pfcuey",
                    "professional-3-2-light_p3cfh4",
                    "professional-3-4-light_fbggfa",
                    "professional-3-5-light_r2nbi6",
                    "professional-3-6-light_j19r0x",
                    "professional-3-7-light_nvf8t6",
                    "professional-3-8-light_wlcwnc",
                    "professional-3-9-light_ozf7pb",
                    "professional-3-10-light_jstl7m",
                    "professional-3-11-light_yoelzb",
                    "professional-3-12-light_v5o7xw",
                    "professional-3-13-light_uy8icy",
                    "professional-3-14-light_bnaxwf",
                    "professional-3-15-light_mgt8hj",
                    "professional-3-16-light_cjo8tz",
                    "professional-3-17-light_jv4dzw",
                    "professional-3-18-light_cr17br",
                    "professional-3-19-light_k5uv7m"
                ]
            },
            {
                "id": "professional-4-cover-light_cxkbri",
                "subtitle": "Volver a vos",
                "title": "Yoga Y Mindfulness",
                "type": "photo",
                "children": [
                    "professional-4-cover-light_cxkbri",
                    "professional-4-1-light_yt528k",
                    "professional-4-2-light_plui92",
                    "professional-4-3-light_zbgtex",
                    "professional-4-4-light_otmpat",
                    "professional-4-5-light_yrscmz",
                    "professional-4-6-light_jgzoor",
                    "professional-4-7-light_ug8v38"
                ]
            },
            {
                "id": "professional-4-cover-light_dmufa6",
                "subtitle": "Maxiking",
                "title": "Colección 2023",
                "type": "photo",
                "children": [
                    "professional-4-cover-light_dmufa6",
                    "professional-5-1-light_whu9zt",
                    "professional-5-2-light_rzxexf",
                    "professional-5-3-light_kfh5cu",
                    "professional-5-4-light_owsej4",
                    "professional-5-6-light_nxbla7",
                    "professional-5-7-light_zacjzt",
                    "professional-5-8-light_vcb33u",
                    "professional-5-9-light_ahv9q3",
                    "professional-5-10-light_nqoosf",
                    "professional-5-11-light_g00uiz",
                    "professional-5-12-light_xbehnl",
                    "professional-5-13-light_ueuwpq",
                    "professional-5-14-light_fxkkz3",
                    "professional-5-15-light_xqjnyq",
                    "professional-5-16-light_ao1fhk"
                ]
            },
            {
                "id": "professional-6-cover-light_webprk",
                "subtitle": "UMA Experience",
                "title": "Lanzamiento UMA Lluvia",
                "type": "photo",
                "children": [
                    "professional-6-cover-light_webprk",
                    "professional-6-1-light_nxjpon",
                    "professional-6-2-light_c7ihn8",
                    "professional-6-3-light_jd5zro",
                    "professional-6-4-light_rigbfi",
                    "professional-6-5-light_ddbofn",
                    "professional-6-6-light_czzfko",
                    "professional-6-7-light_b7olke",
                    "professional-6-8-light_wp4zck",
                    "professional-6-9-light_fwn4ns"
                ]
            },
            {
                "id": "professional-7-cover-light_lvojsu",
                "subtitle": "Ruta de los Pistoleros",
                "title": "Lanzamiento Gravel 2026",
                "type": "photo",
                "children": [
                    "professional-7-cover-light_lvojsu",
                    "professional-7-1-light_etrnbl",
                    "professional-7-2-light_hcjnna",
                    "professional-7-3-light_qjnc0q",
                    "professional-7-4-light_gxhca9",
                    "professional-7-5-light_aetoaq",
                    "professional-7-6-light_gbeksl",
                    "professional-7-7-light_iq6myr",
                    "professional-7-8-light_fxutyd",
                    "professional-7-9-light_ijrfie",
                    "professional-7-10-light_gu3l0c"
                ]
            }
        ],
        "personal": [
            {
                "id": "personal-1-cover-light_hed2t5",
                "title": "Barrenderos",
                "type": "photo",
                "children": [
                    "personal-1-cover-light_hed2t5",
                    "personal-1-2-light_qcvpd8",
                    "personal-1-3-light_rc3zcf",
                    "personal-1-4-light_azz4qb",
                    "personal-1-5-light_ujaqgo",
                    "personal-1-6-light_ixyuyh",
                    "personal-1-7-light_p2jom4"
                ]
            },
            {
                "id": "personal-2-cover-light_mi00jd",
                "title": "Bali",
                "type": "photo",
                "children": [
                    "personal-2-cover-light_mi00jd",
                    "personal-2-1-light_vsmnql",
                    "personal-2-2-light_qeysdw",
                    "personal-2-3-light_ihshn2",
                    "personal-2-4-light_fzh10y",
                    "personal-2-6-light_imu82p",
                    "personal-2-7-light_etvfbu",
                    "personal-2-8-light_jv00e4"
                ]
            },
            {
                "id": "personal-3-cover-light_i1opej",
                "title": "Ñatitas",
                "type": "photo",
                "children": [
                    "personal-3-cover-light_i1opej",
                    "personal-3-1-light_promov",
                    "personal-3-2-light_gib8w1",
                    "personal-3-3-light_zfpdt8",
                    "personal-3-4-light_xnhc5c",
                    "personal-3-5-light_qjjtwm"
                ]
            },
            {
                "id": "personal-4-cover-light_ryntuz",
                "title": "Noel Kempff",
                "type": "photo",
                "children": [
                    "personal-4-cover-light_ryntuz",
                    "personal-4-0-light_giwhwq",
                    "personal-4-1-light_fzvhow",
                    "personal-4-2-light_d8k5wq",
                    "personal-4-3-light_alio49",
                    "personal-4-4-light_zzimsp",
                    "personal-4-5-light_ykqyeh",
                    "personal-4-6-light_modsiq",
                    "personal-4-7-light_schig2",
                    "personal-4-8-light_tgdxoa"
                ]
            },
            {
                "id": "personal-5-cover-light_g3su9c",
                "title": "Quinoa",
                "type": "photo",
                "children": [
                    "personal-5-cover-light_g3su9c",
                    "personal-5-1-light_jv9fef",
                    "personal-5-2-light_zlx56h",
                    "personal-5-3-light_o9bjmc",
                    "personal-5-4-light_l4gkgm",
                    "personal-5-5-light_lqd0ru",
                    "personal-5-6-light_jx6xjv",
                    "personal-5-7-light_vgqtwe",
                    "personal-5-8-light_ejitsk",
                    "personal-5-9-light_rbhsko"
                ]
            },
            {
                "id": "personal-6-cover-light_qvzzcb",
                "title": "Chunchos",
                "type": "photo",
                "children": [
                    "personal-6-cover-light_qvzzcbl",
                    "personal-6-1-light_zifawy",
                    "personal-6-2-light_suihh1",
                    "personal-6-3-light_utprb0",
                    "personal-6-4-light_rmn7fx",
                    "personal-6-5-light_xsmac8",
                    "personal-6-6-light_o4k2hx",
                    "personal-6-7-light_jj8r15",
                    "personal-6-8-light_c0srrs",
                    "personal-6-9-light_qusnsr"
                ]
            },
            {
                "id": "personal-7-cover-light_rh8pi9",
                "title": "Oruro",
                "type": "photo",
                "children": [
                    "personal-7-cover-light_rh8pi9",
                    "personal-7-1-light_eyi9lw",
                    "personal-7-2-light_jyzbwx",
                    "personal-7-3-light_kb0io2",
                    "personal-7-4-light_ekqgst",
                    "personal-7-5-light_sus3fe",
                    "personal-7-6-light_ww6nq9",
                    "personal-7-7-light_pjxz4b",
                    "personal-7-8-light_ulpqph",
                    "personal-7-9-light_gtuwdf",
                    "personal-7-10-light_ttm0sm",
                    "personal-7-11-light_hye9e5",
                    "personal-7-12-light_nq86sp",
                    "personal-7-13-light_ms89zh",
                    "personal-7-14-light_rd1xs7",
                    "personal-7-15-light_lm7jl2",
                    "personal-7-16-light_a9q2gc",
                    "personal-7-17-light_n2fqyg"
                ]
            },
            {
                "id": "personal-8-cover-light_k44qav",
                "title": "Pujllay",
                "type": "photo",
                "children": [
                    "personal-8-cover-light_k44qav",
                    "personal-8-1-light_awvph9",
                    "personal-8-2-light_ssclkh",
                    "personal-8-3-light_es9fmo",
                    "personal-8-4-light_hh3bf6",
                    "personal-8-5-light_yejulr",
                    "personal-8-6-light_cnr4ub",
                    "personal-8-7-light_yvivrp",
                    "personal-8-8-light_csubzc",
                    "personal-8-9-light_peuycd",
                    "personal-8-10-light_slu2g6"
                ]
            }
        ]
    }
}